django_fakeredis/__init__.py
django_fakeredis/fakeredis.py
django_fakeredis/tests.py
example/__init__.py
example/settings.py
django_fakeredis-0.1.2.dist-info/METADATA
django_fakeredis-0.1.2.dist-info/WHEEL
django_fakeredis-0.1.2.dist-info/top_level.txt
django_fakeredis-0.1.2.dist-info/RECORD
