Metadata-Version: 2.1
Name: django-fakeredis
Version: 0.1.2
Summary: Easier to use fakeredis in Django.
Home-page: https://github.com/o3o3o/django-fakeredis
Author: o3o3o
Author-email: o3o3o.me@gmail.com
License: Apache Software License
Platform: UNKNOWN
Classifier: Development Status :: 5 - Production/Stable
Classifier: Environment :: Web Environment
Classifier: Framework :: Django
Classifier: Intended Audience :: Developers
Classifier: License :: OSI Approved :: Apache Software License
Classifier: Operating System :: OS Independent
Classifier: Programming Language :: Python
Classifier: Programming Language :: Python :: 3
Classifier: Programming Language :: Python :: Implementation :: CPython
Classifier: Programming Language :: Python :: Implementation :: PyPy
Classifier: Topic :: Software Development :: Libraries :: Python Modules
Requires-Dist: fakeredis
Requires-Dist: redis
Requires-Dist: django-redis
